rgpl/__init__.py
rgpl/hard_negative_miner/HardNegativeMiner.py
rgpl/hard_negative_miner/HardNegativeWriter.py
rgpl/hard_negative_miner/__init__.py
rgpl/lightning.py
rgpl/query_models/QueryAugmenter.py
rgpl/query_models/QueryGenerator.py
rgpl/query_models/QueryWriter.py
rgpl/query_models/__init__.py
rgpl/query_models/utils.py
rgpl/trainer/EvaluateRetrieval.py
rgpl/trainer/RetriverWriter.py
rgpl/trainer/__init__.py
rgpl/trainer/beir_utils_rewritten.py
rgpl/trainer/hard_negative_dataset.py
rgpl/trainer/loss.py
rgpl/utils.py
rgpl-0.1.0.dist-info/LICENSE
rgpl-0.1.0.dist-info/METADATA
rgpl-0.1.0.dist-info/WHEEL
rgpl-0.1.0.dist-info/RECORD
