Metadata-Version: 2.1
Name: rgpl
Version: 0.1.0
Summary: This package contains our code for the paper [URL].
License: LICENSE
Author: root-goksenin
Author-email: Goksenin.yuksel@outlook.com
Requires-Python: >=3.8,<4.0
Classifier: License :: Other/Proprietary License
Classifier: Programming Language :: Python :: 3
Classifier: Programming Language :: Python :: 3.8
Classifier: Programming Language :: Python :: 3.9
Classifier: Programming Language :: Python :: 3.10
Classifier: Programming Language :: Python :: 3.11
Classifier: Programming Language :: Python :: 3.12
Requires-Dist: beir (>=2.0.0,<3.0.0)
Requires-Dist: easy-elasticsearch (>=0.0.9,<0.0.10)
Requires-Dist: hydra-core (==1.3.2)
Requires-Dist: nltk (>=3.8.1,<4.0.0)
Requires-Dist: omegaconf (==2.3.0)
Requires-Dist: pytorch-lightning (==1.5.10)
Requires-Dist: sentence-transformers (==2.6.1)
Requires-Dist: sentencepiece (>=0.2.0,<0.3.0)
Requires-Dist: tensorboard (==2.14.0)
Requires-Dist: torch (==2.2.2)
Requires-Dist: transformers (==4.39.2)
